{
    "94440b7c-5ea1-410d-a4d3-62fb427f790c": {
        "name": "Instructor",
        "character_uuid": "bee55938-cad6-4c31-9a1e-b0aa241b6d8a",
        "portrait": "D:/Github/Uni/RPG_Project2/Assets/Textures/Atlas/Characters/Single/Guideon-idle.png",
        "text": {
            "en": "Hi, welcome to ThisGame, I'm going to explain you somethings you need to know",
            "fr": ""
        },
        "parent": "06d3041c-a2e1-4cd8-941e-cb11274e8972",
        "next": "392b3a29-ebe0-485f-b4b7-e3f1f3e9b026"
    },
    "392b3a29-ebe0-485f-b4b7-e3f1f3e9b026": {
        "name": "Instructor",
        "character_uuid": "bee55938-cad6-4c31-9a1e-b0aa241b6d8a",
        "portrait": "D:/Github/Uni/RPG_Project2/Assets/Textures/Atlas/Characters/Single/Guideon-idle.png",
        "text": {
            "en": "Firsts, lets learn how to move, Press WASD and explore a bit the island",
            "fr": ""
        },
        "parent": "94440b7c-5ea1-410d-a4d3-62fb427f790c",
        "next": "59e861a0-6830-4dbf-b42b-b3f0f7a9c2c4"
    },
    "59e861a0-6830-4dbf-b42b-b3f0f7a9c2c4": {
        "name": "Instructor",
        "character_uuid": "bee55938-cad6-4c31-9a1e-b0aa241b6d8a",
        "portrait": "D:/Github/Uni/RPG_Project2/Assets/Textures/Atlas/Characters/Single/Guideon-idle.png",
        "text": {
            "en": "Come to me onces you do it",
            "fr": ""
        },
        "parent": "392b3a29-ebe0-485f-b4b7-e3f1f3e9b026",
        "signals": {
            "parent": "59e861a0-6830-4dbf-b42b-b3f0f7a9c2c4",
            "AddMission": {
                "String": "mission;testing3"
            },
            "SetNpcStatusByID": {
                "Vector2": {
                    "x": "9",
                    "y": "1"
                }
            }
        }
    },
    "root": {
        "conditions": [
            {
                "Char9_State": {
                    "value": 0,
                    "operator": "equal",
                    "type": "int"
                },
                "parent": "root",
                "next": "94440b7c-5ea1-410d-a4d3-62fb427f790c"
            },
            {
                "Char9_State": {
                    "value": 1,
                    "operator": "equal",
                    "type": "int"
                },
                "parent": "root",
                "next": "fbe536ad-4036-4349-a88f-eebaef3cc321"
            },
            {
                "parent": "root",
                "next": "73eeb42c-c74c-4d79-905e-88d89565b163",
                "Char9_State": {
                    "value": 2,
                    "operator": "equal",
                    "type": "int"
                }
            },
            {
                "Char9_State": {
                    "value": 3,
                    "operator": "equal",
                    "type": "int"
                },
                "parent": "root",
                "next": "b85f1c4a-0142-441e-a2fb-3c4d4209bbbd"
            }
        ]
    },
    "fbe536ad-4036-4349-a88f-eebaef3cc321": {
        "name": "Instructor",
        "character_uuid": "bee55938-cad6-4c31-9a1e-b0aa241b6d8a",
        "portrait": "D:/Github/Uni/RPG_Project2/Assets/Textures/Atlas/Characters/Single/Guideon-idle.png",
        "text": {
            "en": "Let me see...",
            "fr": ""
        },
        "parent": "29fa9086-7629-430f-893d-7ef965c2d7c2",
        "signals": {
            "parent": "fbe536ad-4036-4349-a88f-eebaef3cc321",
            "CheckIfMissionCompleted": {
                "String": "mission;testing3"
            }
        },
        "conditions": [
            {
                "parent": "fbe536ad-4036-4349-a88f-eebaef3cc321",
                "HasCompletedMission": {
                    "value": true,
                    "operator": "equal",
                    "type": "boolean"
                },
                "next": "58d44154-5750-4205-a9bf-a7c6b77661b0"
            },
            {
                "parent": "fbe536ad-4036-4349-a88f-eebaef3cc321",
                "next": "cf901b47-3a37-4278-9c41-37eef8f3a46d"
            }
        ]
    },
    "58d44154-5750-4205-a9bf-a7c6b77661b0": {
        "name": "Instructor",
        "character_uuid": "bee55938-cad6-4c31-9a1e-b0aa241b6d8a",
        "portrait": "D:/Github/Uni/RPG_Project2/Assets/Textures/Atlas/Characters/Single/Guideon-idle.png",
        "text": {
            "en": "Perfect! Now lets see what can we do",
            "fr": ""
        },
        "parent": "0b2b9039-a09a-41a7-a3c1-01c61c6bdc21",
        "signals": {
            "parent": "58d44154-5750-4205-a9bf-a7c6b77661b0",
            "RemoveMission": {
                "String": "mission;testing3"
            },
            "SetNpcStatusByID": {
                "Vector2": {
                    "x": "9",
                    "y": "2"
                }
            }
        }
    },
    "cf901b47-3a37-4278-9c41-37eef8f3a46d": {
        "name": "Instructor",
        "character_uuid": "bee55938-cad6-4c31-9a1e-b0aa241b6d8a",
        "portrait": "D:/Github/Uni/RPG_Project2/Assets/Textures/Atlas/Characters/Single/Guideon-idle.png",
        "text": {
            "en": "As I said, WALK NOW!",
            "fr": ""
        },
        "parent": "cf18d283-29cd-40bb-8273-ca58d49fa0d0"
    },
    "__editor": {
        "root": {
            "uuid": "root",
            "offset": [
                40,
                100
            ]
        },
        "dialogues": [
            {
                "uuid": "94440b7c-5ea1-410d-a4d3-62fb427f790c",
                "offset": [
                    760,
                    -420
                ]
            },
            {
                "uuid": "392b3a29-ebe0-485f-b4b7-e3f1f3e9b026",
                "offset": [
                    1180,
                    -420
                ]
            },
            {
                "uuid": "59e861a0-6830-4dbf-b42b-b3f0f7a9c2c4",
                "offset": [
                    1580,
                    -420
                ]
            },
            {
                "uuid": "fbe536ad-4036-4349-a88f-eebaef3cc321",
                "offset": [
                    700,
                    80
                ]
            },
            {
                "uuid": "58d44154-5750-4205-a9bf-a7c6b77661b0",
                "offset": [
                    2140,
                    -80
                ]
            },
            {
                "uuid": "cf901b47-3a37-4278-9c41-37eef8f3a46d",
                "offset": [
                    2560,
                    180
                ]
            },
            {
                "uuid": "73eeb42c-c74c-4d79-905e-88d89565b163",
                "offset": [
                    700,
                    540
                ]
            },
            {
                "uuid": "4da1f5c9-eb82-44ab-9987-a297ad4f91db",
                "offset": [
                    1820,
                    760
                ]
            },
            {
                "uuid": "60cc6a7e-1754-4307-bfd8-cecfeead6053",
                "offset": [
                    2640,
                    1120
                ]
            },
            {
                "uuid": "529a0705-2c82-4f9a-a368-47598ac1da5b",
                "offset": [
                    2640,
                    740
                ]
            },
            {
                "uuid": "b85f1c4a-0142-441e-a2fb-3c4d4209bbbd",
                "offset": [
                    720,
                    1240
                ]
            },
            {
                "uuid": "62092bef-cd88-45f0-a566-1c762a69ba54",
                "offset": [
                    1520,
                    1800
                ]
            },
            {
                "uuid": "7e117f3a-07c5-41dc-b0dd-71f24bdbb7ca",
                "offset": [
                    1520,
                    1420
                ]
            },
            {
                "uuid": "b63323d4-559a-499d-9039-e68c7c69fbf3",
                "offset": [
                    1960,
                    1480
                ]
            },
            {
                "uuid": "8a020ff4-ab00-45c9-a2a2-26d0a3e467e2",
                "offset": [
                    1100,
                    760
                ]
            },
            {
                "uuid": "56c9cc0f-23c7-4a43-acf5-59d1a706599a",
                "offset": [
                    2460,
                    1640
                ]
            }
        ],
        "conditions": [
            {
                "uuid": "06d3041c-a2e1-4cd8-941e-cb11274e8972",
                "offset": [
                    340,
                    -280
                ],
                "parent": "root"
            },
            {
                "uuid": "29fa9086-7629-430f-893d-7ef965c2d7c2",
                "offset": [
                    340,
                    120
                ],
                "parent": "root"
            },
            {
                "uuid": "0b2b9039-a09a-41a7-a3c1-01c61c6bdc21",
                "offset": [
                    1620,
                    120
                ],
                "parent": "fbe536ad-4036-4349-a88f-eebaef3cc321"
            },
            {
                "uuid": "cf18d283-29cd-40bb-8273-ca58d49fa0d0",
                "offset": [
                    1620,
                    460
                ],
                "collapsed": true,
                "parent": "fbe536ad-4036-4349-a88f-eebaef3cc321"
            },
            {
                "uuid": "cd5a644e-19f8-4b87-a23c-73bb7bddf33c",
                "offset": [
                    340,
                    560
                ],
                "parent": "root"
            },
            {
                "uuid": "9f2e1e54-7d1d-43cf-8bba-cb7fdbf1975c",
                "offset": [
                    2220,
                    920
                ],
                "parent": "4da1f5c9-eb82-44ab-9987-a297ad4f91db"
            },
            {
                "uuid": "9948b962-4de3-4971-9e78-9b980328bd68",
                "offset": [
                    2220,
                    1260
                ],
                "collapsed": true,
                "parent": "4da1f5c9-eb82-44ab-9987-a297ad4f91db"
            },
            {
                "uuid": "a78ce74f-5b7d-44f4-b00d-8f097a944cf2",
                "offset": [
                    340,
                    960
                ],
                "parent": "root"
            }
        ],
        "signals": [
            {
                "uuid": "0ae6e22a-ce50-411f-a1a7-cfb076629085",
                "offset": [
                    2020,
                    -520
                ],
                "parent": "59e861a0-6830-4dbf-b42b-b3f0f7a9c2c4"
            },
            {
                "uuid": "e5693104-80f5-48c3-bd63-112cd7652d82",
                "offset": [
                    1100,
                    -40
                ],
                "parent": "fbe536ad-4036-4349-a88f-eebaef3cc321"
            },
            {
                "uuid": "9b277e93-af34-4d8e-b1bc-de11e0b1ae61",
                "offset": [
                    2580,
                    -260
                ],
                "parent": "58d44154-5750-4205-a9bf-a7c6b77661b0"
            },
            {
                "uuid": "06c4fb6f-4f00-49cc-93ce-a5df5d7b49d5",
                "offset": [
                    2200,
                    620
                ],
                "parent": "4da1f5c9-eb82-44ab-9987-a297ad4f91db"
            },
            {
                "uuid": "df35f2d2-bb1a-48d7-a7e3-3cdb204ab314",
                "offset": [
                    3080,
                    800
                ],
                "parent": "529a0705-2c82-4f9a-a368-47598ac1da5b"
            },
            {
                "uuid": "b0c59c21-4c6f-4b92-8e91-ed5195be24c2",
                "offset": [
                    1480,
                    600
                ],
                "parent": "8a020ff4-ab00-45c9-a2a2-26d0a3e467e2"
            }
        ],
        "choices": [
            {
                "uuid": "0b34ebc3-86f2-4fe1-8d68-1177c494ee7d",
                "offset": [
                    1140,
                    1280
                ],
                "parent": "b85f1c4a-0142-441e-a2fb-3c4d4209bbbd"
            },
            {
                "uuid": "7e4b4475-b164-4dda-b883-2e382e18bf37",
                "offset": [
                    1140,
                    1520
                ],
                "parent": "b85f1c4a-0142-441e-a2fb-3c4d4209bbbd"
            }
        ]
    },
    "73eeb42c-c74c-4d79-905e-88d89565b163": {
        "name": "Instructor",
        "character_uuid": "bee55938-cad6-4c31-9a1e-b0aa241b6d8a",
        "portrait": "D:/Github/Uni/RPG_Project2/Assets/Textures/Atlas/Characters/Single/Guideon-idle.png",
        "text": {
            "en": "Okay, now lets fight!",
            "fr": ""
        },
        "parent": "cd5a644e-19f8-4b87-a23c-73bb7bddf33c",
        "next": "8a020ff4-ab00-45c9-a2a2-26d0a3e467e2"
    },
    "4da1f5c9-eb82-44ab-9987-a297ad4f91db": {
        "name": "Instructor",
        "character_uuid": "bee55938-cad6-4c31-9a1e-b0aa241b6d8a",
        "portrait": "D:/Github/Uni/RPG_Project2/Assets/Textures/Atlas/Characters/Single/Guideon-idle.png",
        "text": {
            "en": "Wow",
            "fr": ""
        },
        "parent": "8a020ff4-ab00-45c9-a2a2-26d0a3e467e2",
        "signals": {
            "parent": "4da1f5c9-eb82-44ab-9987-a297ad4f91db",
            "CheckIfWonCombat": {}
        },
        "conditions": [
            {
                "parent": "4da1f5c9-eb82-44ab-9987-a297ad4f91db",
                "HasWonCombat": {
                    "value": true,
                    "operator": "equal",
                    "type": "boolean"
                },
                "next": "529a0705-2c82-4f9a-a368-47598ac1da5b"
            },
            {
                "parent": "4da1f5c9-eb82-44ab-9987-a297ad4f91db",
                "next": "60cc6a7e-1754-4307-bfd8-cecfeead6053"
            }
        ]
    },
    "60cc6a7e-1754-4307-bfd8-cecfeead6053": {
        "name": "Instructor",
        "character_uuid": "bee55938-cad6-4c31-9a1e-b0aa241b6d8a",
        "portrait": "D:/Github/Uni/RPG_Project2/Assets/Textures/Atlas/Characters/Single/Guideon-idle.png",
        "text": {
            "en": "Don't worry,I give you anoher try",
            "fr": ""
        },
        "parent": "9948b962-4de3-4971-9e78-9b980328bd68"
    },
    "529a0705-2c82-4f9a-a368-47598ac1da5b": {
        "name": "Instructor",
        "character_uuid": "bee55938-cad6-4c31-9a1e-b0aa241b6d8a",
        "portrait": "D:/Github/Uni/RPG_Project2/Assets/Textures/Atlas/Characters/Single/Guideon-idle.png",
        "text": {
            "en": "You have talent, you are good. Talk to me when you are ready",
            "fr": ""
        },
        "parent": "9f2e1e54-7d1d-43cf-8bba-cb7fdbf1975c",
        "signals": {
            "parent": "529a0705-2c82-4f9a-a368-47598ac1da5b",
            "SetNpcStatusByID": {
                "Vector2": {
                    "x": "9",
                    "y": "3"
                }
            }
        }
    },
    "b85f1c4a-0142-441e-a2fb-3c4d4209bbbd": {
        "name": "Instructor",
        "character_uuid": "bee55938-cad6-4c31-9a1e-b0aa241b6d8a",
        "portrait": "D:/Github/Uni/RPG_Project2/Assets/Textures/Atlas/Characters/Single/Guideon-idle.png",
        "text": {
            "en": "Are you ready?",
            "fr": ""
        },
        "parent": "a78ce74f-5b7d-44f4-b00d-8f097a944cf2",
        "choices": [
            {
                "text": {
                    "en": "Yes",
                    "fr": ""
                },
                "next": "7e117f3a-07c5-41dc-b0dd-71f24bdbb7ca",
                "parent": "b85f1c4a-0142-441e-a2fb-3c4d4209bbbd"
            },
            {
                "text": {
                    "en": "No",
                    "fr": ""
                },
                "next": "62092bef-cd88-45f0-a566-1c762a69ba54",
                "parent": "b85f1c4a-0142-441e-a2fb-3c4d4209bbbd"
            }
        ]
    },
    "62092bef-cd88-45f0-a566-1c762a69ba54": {
        "name": "Instructor",
        "character_uuid": "bee55938-cad6-4c31-9a1e-b0aa241b6d8a",
        "portrait": "D:/Github/Uni/RPG_Project2/Assets/Textures/Atlas/Characters/Single/Guideon-idle.png",
        "text": {
            "en": "When you are reaydu, just talk to me",
            "fr": ""
        },
        "parent": "7e4b4475-b164-4dda-b883-2e382e18bf37"
    },
    "7e117f3a-07c5-41dc-b0dd-71f24bdbb7ca": {
        "name": "Instructor",
        "character_uuid": "bee55938-cad6-4c31-9a1e-b0aa241b6d8a",
        "portrait": "D:/Github/Uni/RPG_Project2/Assets/Textures/Atlas/Characters/Single/Guideon-idle.png",
        "text": {
            "en": "Its been a pleasure, see you!",
            "fr": ""
        },
        "parent": "0b34ebc3-86f2-4fe1-8d68-1177c494ee7d",
        "next": "b63323d4-559a-499d-9039-e68c7c69fbf3"
    },
    "b63323d4-559a-499d-9039-e68c7c69fbf3": {
        "name": "Cassian",
        "character_uuid": "9e488680-eba3-4172-8361-67b08867e5ab",
        "portrait": "D:/Github/Uni/RPG_Project2/Assets/Textures/Atlas/Characters/Single/Cassian-early-idle.png",
        "text": {
            "en": "Bye!",
            "fr": ""
        },
        "parent": "7e117f3a-07c5-41dc-b0dd-71f24bdbb7ca",
        "next": "56c9cc0f-23c7-4a43-acf5-59d1a706599a"
    },
    "8a020ff4-ab00-45c9-a2a2-26d0a3e467e2": {
        "name": "Instructor",
        "character_uuid": "bee55938-cad6-4c31-9a1e-b0aa241b6d8a",
        "portrait": "D:/Github/Uni/RPG_Project2/Assets/Textures/Atlas/Characters/Single/Guideon-idle.png",
        "text": {
            "en": "...",
            "fr": ""
        },
        "parent": "73eeb42c-c74c-4d79-905e-88d89565b163",
        "next": "4da1f5c9-eb82-44ab-9987-a297ad4f91db",
        "signals": {
            "parent": "8a020ff4-ab00-45c9-a2a2-26d0a3e467e2",
            "StartCombat": {
                "String": "9"
            }
        }
    },
    "56c9cc0f-23c7-4a43-acf5-59d1a706599a": {
        "name": "Artis",
        "character_uuid": "66658753-5bc8-4f86-ad55-c5607a3fd336",
        "portrait": "D:/Github/Uni/RPG_Project2/Assets/Textures/Atlas/Characters/Single/Artis-early-idle.png",
        "text": {
            "en": "DEBUG: DO A TP TO ANOTHER MAP",
            "fr": ""
        },
        "parent": "b63323d4-559a-499d-9039-e68c7c69fbf3"
    }
}